arakhne/__init__.py
arakhne/arakhne.py
arakhne/common/__init__.py
arakhne/common/functions.py
arakhne/core/__init__.py
arakhne/core/language_checker.py
arakhne/core/settings.py
arakhne/corpus/__init__.py
arakhne/corpus/base_corpus.py
arakhne/corpus/cltk_corpus.py
arakhne/corpus/corpus_io.py
arakhne/corpus/english_corpus.py
arakhne/corpus/greek_corpus.py
arakhne/corpus/latin_corpus.py
arakhne/corpus/nltk_corpus.py
arakhne/corpus/files/__init__.py
arakhne/corpus/files/base_file.py
arakhne/corpus/files/csv_file.py
arakhne/doc/__init__.py
arakhne/doc/base_doc.py
arakhne/doc/cltk_doc.py
arakhne/doc/english_doc.py
arakhne/doc/greek_doc.py
arakhne/doc/latin_doc.py
arakhne/doc/nltk_doc.py
arakhne/fixtures/__init__.py
arakhne/get/__init__.py
arakhne/get/get_base.py
arakhne/get/get_cltk.py
arakhne/get/get_nltk.py
arakhne/settings/__init__.py
arakhne/settings/defaults.py
arakhne/settings/setup.py
arakhne/setup/__init__.py
arakhne/setup/install.py
arakhne/setup/validate.py
arakhne/stopwords/__init__.py
arakhne/stopwords/stopwords.py
arakhne/tests/__init__.py
arakhne/tests/arakhne_test.py
arakhne-0.3.1.dist-info/DESCRIPTION.rst
arakhne-0.3.1.dist-info/LICENSE.txt
arakhne-0.3.1.dist-info/METADATA
arakhne-0.3.1.dist-info/RECORD
arakhne-0.3.1.dist-info/WHEEL
arakhne-0.3.1.dist-info/metadata.json
arakhne-0.3.1.dist-info/top_level.txt
