Metadata-Version: 2.0
Name: arakhne
Version: 0.3.1
Summary: Arakhne Classical Text Loom for Corpus-Based Analytics
Home-page: https://github.com/thePortus/arakhne
Author: David J. Thomas
Author-email: dave.a.base@gmail.com
License: UNKNOWN
Download-URL: https://github.com/thePortus/arakhne/archive/master.zip
Keywords: nlp,nltk,cltk
Platform: UNKNOWN
Classifier: Programming Language :: Python
Classifier: Programming Language :: Python :: 3
Classifier: Development Status :: 3 - Alpha
Classifier: Environment :: Other Environment
Classifier: Intended Audience :: Education
Classifier: License :: OSI Approved :: MIT License
Classifier: Operating System :: MacOS :: MacOS X
Classifier: Operating System :: POSIX :: Linux
Classifier: Topic :: Software Development :: Libraries :: Python Modules
Classifier: Topic :: Text Processing :: Linguistic
Classifier: Topic :: Sociology :: History
Requires-Dist: nltk
Requires-Dist: cltk
